bkpk/__init__.py
bkpk/__main__.py
bkpk/cli.py
bkpk/helpers.py
bkpk/models.py
bkpk/pack.py
bkpk/unpack.py
bkpk-0.2.7.dist-info/entry_points.txt
bkpk-0.2.7.dist-info/LICENSE
bkpk-0.2.7.dist-info/WHEEL
bkpk-0.2.7.dist-info/METADATA
bkpk-0.2.7.dist-info/RECORD
