Metadata-Version: 2.1
Name: bkpk
Version: 0.2.7
Summary: A super simple and lightweight zip- and unzip tool.
Author-email: nsde <mail@onlix.me>
Classifier: License :: OSI Approved :: MIT License
Project-URL: Home, https://github.com/nsde/bkpk
